[
    {
        "id": "marker99",
        "x": 8530,
        "y": 7600,
        "url": "temples/krishnabalramtempleisckon.html",
        "maxZoom": 0.4,
        "color": "green",
        "label": "Krishna Balaram Temple"
    },
    {
        "id": "marker88",
        "x": 8453,
        "y": 7560,
        "url": "temples/krishnabalramtempleisckon.html",
        "maxZoom": 0.4,
        "color": "green",
        "label": "Old Shri Radhavallabh Temple"
    },
    {
        "id": "marker2",
        "x": 9032,
        "y": 7500,
        "url": "temples/shriradhavallabhtemple.html",
        "color": "green",
        "maxZoom": 1.5,
        "label": "Sewa Kunj View 2, Vrindavan"
    },
    {
        "id": "marker3",
        "x": 8369,
        "y": 7380,
        "url": "stuban",
        "maxZoom": 1.5,
        "color": "green",
        "label": "Sri Madan Mohan Temple, Vrindavan"
    },
    {
        "id": "marker4",
        "x": 8885,
        "y": 7000,
        "url": "stuban",
        "maxZoom": 1.5,
        "color": "green",
        "label": "Other Side of Yamuna, Vrindavan"
    },
    {
        "id": "marker5",
        "x": 9611,
        "y": 7370,
        "url": "stuban",
        "maxZoom": 1.5,
        "color": "green",
        "label": "Shri Radha Gopinath Temple, Vrindavan"
    },
    {
        "id": "marker6",
        "x": 8474,
        "y": 7500,
        "url": "stuban",
        "maxZoom": 1.5,
        "color": "green",
        "label": "Shri Banke Bihari Vrindavan"
    },
    {
        "id": "marker7",
        "x": 9011,
        "y": 7210,
        "url": "stuban",
        "maxZoom": 1.5,
        "color": "green",
        "label": "Inside View of Imlitala Temple, Vrindavan"
    },
    {
        "id": "marker8",
        "x": 9728,
        "y": 7200,
        "url": "stuban",
        "color": "green",
        "maxZoom": 1.5,
        "label": "Shriji Ka Mandir, Vrindavan"
    },
    {
        "id": "marker9",
        "x": 9569,
        "y": 7453,
        "url": "stuban",
        "maxZoom": 1.5,
        "color": "green",
        "label": "Shri Gopeshwar Mahadev, Vrindavan"
    },
    {
        "id": "marker10",
        "x": 9369,
        "y": 7663,
        "url": "stuban",
        "maxZoom": 1.5,
        "color": "green",
        "label": "Shri Chaitanya Mahaprabhu Baithak, Radha Kund"
    },
    {
        "id": "marker11",
        "x": 9401,
        "y": 7154,
        "url": "stuban",
        "maxZoom": 1.5,
        "color": "green",
        "label": "Maan Sarovar, Vrindavan"
    },
    {
        "id": "marker13",
        "x": 9664,
        "y": 7512,
        "url": "stuban",
        "maxZoom": 1.5,
        "color": "green",
        "label": "Shri Brahma Kund, Vrindavan"
    },
    {
        "id": "marker14",
        "x": 8464,
        "y": 7430,
        "url": "stuban",
        "maxZoom": 1.5,
        "color": "green",
        "label": "Kalideh (Kaaliya Ghat), Vrindavan"
    },
    {
        "id": "marker15",
        "x": 9148,
        "y": 7150,
        "url": "stuban",
        "color": "green",
        "maxZoom": 1.5,
        "label": "Keshi Ghat, Vrindavan"
    },
    {
        "id": "marker16",
        "x": 8622,
        "y": 7657,
        "url": "stuban",
        "maxZoom": 1.5,
        "color": "green",
        "label": "Davanal Kund, Vrindavan"
    },
    {
        "id": "marker17",
        "x": 9158,
        "y": 7550,
        "color": "red",
        "url": "stuban",
        "maxZoom": 1.5,
        "label": "Old Radha Govinddev temple"
    },
    {
        "id": "marker18",
        "x": 9085,
        "y": 7430,
        "url": "stuban",
        "maxZoom": 1.5,
        "color": "green",
        "label": "NidhiVan"
    },
    {
        "id": "marker19",
        "x": 9474,
        "y": 7250,
        "url": "stuban",
        "maxZoom": 1.5,
        "color": "green",
        "label": "Sri Radha Raman's Appearance place, Vrindavan"
    }
    ,
    {
        "id": "marker20",
        "x": 9253,
        "y": 7379,
        "url": "stuban",
        "maxZoom": 1.5,
        "color": "green",
        "label": "Yamuna From Sri Gopinath Bhawan, Imlitala, Vrindavan"
    },
    {
        "id": "marker21",
        "x": 9085,
        "y": 7760,
        "url": "stuban",
        "maxZoom": 1.5,
        "color": "green",
        "label": "Shri Yamuna Devi, Vrindavan"
    },
    {
        "id": "marker22",
        "x": 9064,
        "y": 7948,
        "url": "stuban",
        "maxZoom": 1.5,
        "color": "green",
        "label": "Lane near Old Raas Mandal near Yamuna, Vrindavan"
    },
    {
        "id": "marker23",
        "x": 9158,
        "y": 7100,
        "url": "stuban",
        "maxZoom": 1.5,
        "color": "green",
        "label": "Shri Yamuna Mandir, Keshi Ghat, Vrindavan"
    },
    {
        "id": "marker24",
        "x": 9158,
        "y": 7100,
        "url": "stuban",
        "maxZoom": 1.5,
        "color": "green",
        "label": "Shri Yamuna Mandir, Keshi Ghat, Vrindavan"
    },










    
    {
        "id": "marker1",
        "X": 4956,
        "y": 4652,
        "label": "Kokila ban bihari",
        "url": "stuban",
        "maxZoom": 1.5,
        "color": "red"
    },
    {
        "id": "marker2",
        "X": 4999,
        "y": 4699,
        "label": "Rash mandal",
        "url": "stuban",
        "maxZoom": 1.5,
        "color": "red"
    },
    {
        "id": "marker3",
        "X": 5419,
        "y": 4707,
        "label": "Pandav gufa",
        "url": "stuban",
        "maxZoom": 1.5,
        "color": "red"
    },
    {
        "id": "marker4",
        "X": 5298,
        "y": 4812,
        "label": "Sanidav mandir",
        "url": "stuban",
        "maxZoom": 1.5,
        "color": "red"
    },
    {
        "id": "marker5",
        "X": 5263,
        "y": 4856,
        "label": "Mahaprabhu Vallabhacharya",
        "url": "stuban",
        "maxZoom": 1.5,
        "color": "red"
    },
    {
        "id": "marker6",
        "X": 5184,
        "y": 5040,
        "label": "Radhakant Mandir",
        "url": "stuban",
        "maxZoom": 1.5,
        "color": "red"
    },
    {
        "id": "marker7",
        "X": 5109,
        "y": 5099,
        "label": "Ter kadamba pond",
        "url": "stuban",
        "maxZoom": 1.5,
        "color": "red"
    },
    {
        "id": "marker8",
        "X": 5198,
        "y": 5199,
        "label": "Goswami",
        "url": "stuban",
        "maxZoom": 1.5,
        "color": "red"
    },
    {
        "id": "marker9",
        "X": 5175,
        "y": 5247,
        "label": "Nandishwar Mahadev",
        "url": "stuban",
        "maxZoom": 1.5,
        "color": "red"
    },
    {
        "id": "marker10",
        "X": 4563,
        "y": 4849,
        "label": "Yugal Kishore Mandir",
        "url": "stuban",
        "maxZoom": 1.5,
        "color": "red"
    },
    {
        "id": "marker11",
        "X": 4702,
        "y": 5150,
        "label": "Mahaprabhu Vallabhacharya",
        "url": "stuban",
        "maxZoom": 1.5,
        "color": "red"
    },
    {
        "id": "marker12",
        "X": 4725,
        "y": 5201,
        "label": "Chaitanya Mahaprabhu",
        "url": "stuban",
        "maxZoom": 1.5,
        "color": "red"
    },
    {
        "id": "marker13",
        "X": 4668,
        "y": 5296,
        "label": "Sanatan Goswami",
        "url": "stuban",
        "maxZoom": 1.5,
        "color": "red"
    },
    {
        "id": "marker14",
        "X": 4712,
        "y": 5387,
        "label": "Vrinda kund",
        "url": "stuban",
        "maxZoom": 1.5,
        "color": "red"
    },
    {
        "id": "marker15",
        "X": 4695,
        "y": 5337,
        "label": "Gupat pond",
        "url": "stuban",
        "maxZoom": 1.5,
        "color": "red"
    },
    {
        "id": "marker16",
        "X": 4990,
        "y": 5430,
        "label": "How Bilau/ Yashoda pond",
        "url": "stuban",
        "maxZoom": 1.5,
        "color": "red"
    },
    {
        "id": "marker17",
        "X": 4831,
        "y": 5470,
        "label": "Madhusudhan pond",
        "url": "stuban",
        "maxZoom": 1.5,
        "color": "red"
    },
    {
        "id": "marker18",
        "X": 5135,
        "y": 5323,
        "label": "Nanda bhaman",
        "url": "stuban",
        "maxZoom": 1.5,
        "color": "red"
    },
    {
        "id": "marker19",
        "X": 4733,
        "y": 5247,
        "label": "Pavan sharobar",
        "url": "stuban",
        "maxZoom": 1.5,
        "color": "red"
    },
    {
        "id": "marker20",
        "X": 5051,
        "y": 5166,
        "label": "Moti kundh",
        "url": "stuban",
        "maxZoom": 1.5,
        "color": "red"
    },
    {
        "id": "marker21",
        "X": 4964,
        "y": 4983,
        "label": "Gopi Kund",
        "url": "stuban",
        "maxZoom": 1.5,
        "color": "red"
    },
    {
        "id": "marker22",
        "X": 4960,
        "y": 5038,
        "label": "Fulbari kund",
        "url": "stuban",
        "maxZoom": 1.5,
        "color": "red"
    },
    {
        "id": "marker23",
        "X": 4985,
        "y": 4941,
        "label": "Gaudharvan Kund",
        "url": "stuban",
        "maxZoom": 1.5,
        "color": "red"
    },
    {
        "id": "marker24",
        "X": 4979,
        "y": 4883,
        "label": "Gandharv kund",
        "url": "stuban",
        "maxZoom": 1.5,
        "color": "red"
    },
    {
        "id": "marker25",
        "X": 4993,
        "y": 4835,
        "label": "gandhogar kund",
        "url": "stuban",
        "maxZoom": 1.5,
        "color": "red"
    },
    {
        "id": "marker26",
        "X": 4919,
        "y": 4773,
        "label": "Ratnakar Sarovar",
        "url": "stuban",
        "maxZoom": 1.5,
        "color": "red"
    },
    {
        "id": "marker27",
        "X": 4787,
        "y": 4894,
        "label": "Jalbhar kund",
        "url": "stuban",
        "maxZoom": 1.5,
        "color": "red"
    },
    {
        "id": "marker28",
        "X": 4785,
        "y": 4938,
        "label": "Bihar kund",
        "url": "stuban",
        "maxZoom": 1.5,
        "color": "red"
    },
    {
        "id": "marker29",
        "X": 4817,
        "y": 4992,
        "label": "Belvan Kund",
        "url": "stuban",
        "maxZoom": 1.5,
        "color": "red"
    },
    {
        "id": "marker30",
        "X": 4668,
        "y": 5063,
        "label": "Kam sharovar",
        "url": "stuban",
        "maxZoom": 1.5,
        "color": "red"
    },
    {
        "id": "marker31",
        "X": 4144,
        "y": 5203,
        "label": "Yashodha kund",
        "url": "stuban",
        "maxZoom": 1.5,
        "color": "red"
    },
    {
        "id": "marker32",
        "X": 5289,
        "y": 4747,
        "label": "Panihari kund",
        "url": "stuban",
        "maxZoom": 1.5,
        "color": "red"
    },
    {
        "id": "marker33",
        "X": 5416,
        "y": 4658,
        "label": "Pandhav Gufa",
        "url": "stuban",
        "maxZoom": 1.5,
        "color": "red"
    },
    {
        "id": "marker34",
        "X": 5409,
        "y": 4656,
        "label": "Pandhav Gannga",
        "url": "stuban",
        "maxZoom": 1.5,
        "color": "red"
    },
    {
        "id": "marker35",
        "X": 4717,
        "y": 5539,
        "label": "Charan pahadhi",
        "url": "stuban",
        "maxZoom": 1.5,
        "color": "red"
    },
    {
        "id": "marker36",
        "X": 4768,
        "y": 5091,
        "label": "Nandhgram van",
        "url": "stuban",
        "maxZoom": 1.5,
        "color": "red"
    },
    {
        "id": "marker37",
        "X": 4372,
        "y": 4889,
        "label": "Sicha van",
        "url": "stuban",
        "maxZoom": 1.5,
        "color": "red"
    },
    {
        "id": "marker38",
        "X": 5309,
        "y": 4986,
        "label": "kishuri van",
        "url": "stuban",
        "maxZoom": 1.5,
        "color": "red"
    },
    {
        "id": "marker39",
        "X": 5117,
        "y": 5454,
        "label": "Nandh kund",
        "url": "stuban",
        "maxZoom": 1.5,
        "color": "red"
    },
    {
        "id": "marker40",
        "X": 5294,
        "y": 5391,
        "label": "Kirshna kund",
        "url": "stuban",
        "maxZoom": 1.5,
        "color": "red"
    }
]

